gen3authz/__init__.py
gen3authz/client/__init__.py
gen3authz/client/arborist/__init__.py
gen3authz/client/arborist/async_client.py
gen3authz/client/arborist/base.py
gen3authz/client/arborist/client.py
gen3authz/client/arborist/errors.py
gen3authz/client/base.py
gen3authz/client/errors.py
gen3authz/utils.py
gen3authz-3.0.0.dist-info/METADATA
gen3authz-3.0.0.dist-info/WHEEL
gen3authz-3.0.0.dist-info/licenses/LICENSE
gen3authz-3.0.0.dist-info/licenses/NOTICE
gen3authz-3.0.0.dist-info/RECORD
