Metadata-Version: 2.4
Name: gen3authz
Version: 3.0.0
Summary: Gen3 authz client
License: Apache-2.0
License-File: LICENSE
License-File: NOTICE
Author: CTDS UChicago
Author-email: cdis@uchicago.edu
Requires-Python: >=3.13,<4.0
Classifier: License :: OSI Approved :: Apache Software License
Classifier: Programming Language :: Python :: 3
Classifier: Programming Language :: Python :: 3.13
Classifier: Programming Language :: Python :: 3.14
Requires-Dist: backoff (>=2.2.1,<3.0.0)
Requires-Dist: cdiserrors (<2.0.0)
Requires-Dist: httpx (>=0.20.0,<1.0.0)
Requires-Dist: six (>=1.16.0,<2.0.0)
Requires-Dist: sniffio (>=1.3.1)
